cobra.py
cobra_meta-1.2.3.dist-info/METADATA
cobra_meta-1.2.3.dist-info/WHEEL
cobra_meta-1.2.3.dist-info/entry_points.txt
cobra_meta-1.2.3.dist-info/top_level.txt
cobra_meta-1.2.3.dist-info/RECORD
