Metadata-Version: 2.1
Name: cobra-meta
Version: 1.2.3
Summary: COBRA (Contig Overlap Based Re-Assembly) is a bioinformatics tool to get higher quality viral genomes assembled from metagenomes of short paired-end reads. COBRA was written in Python. COBRA has so far only been tested on assembled contigs from metaSPAdes, IDBA_UD, and MEGAHIT.
Home-page: https://github.com/linxingchen/cobra
Author: LINXING CHEN
Requires-Dist: biopython
Requires-Dist: pysam
